aliyunsdkbeian/__init__.py
aliyunsdkbeian/request/__init__.py
aliyunsdkbeian/request/v20160810/DeleteUnbeianIpCheckTypeRequest.py
aliyunsdkbeian/request/v20160810/GetMainDomainRequest.py
aliyunsdkbeian/request/v20160810/InsertUnbeianIpCheckTypeRequest.py
aliyunsdkbeian/request/v20160810/ListUnbeianIpCheckTypeRequest.py
aliyunsdkbeian/request/v20160810/ManageAccessorDomainRequest.py
aliyunsdkbeian/request/v20160810/ManageAccessorDomainWhiteListRequest.py
aliyunsdkbeian/request/v20160810/ManageAccessorIpRequest.py
aliyunsdkbeian/request/v20160810/QueryAccessorDomainListRequest.py
aliyunsdkbeian/request/v20160810/QueryAccessorDomainRequest.py
aliyunsdkbeian/request/v20160810/QueryAccessorDomainStatusRequest.py
aliyunsdkbeian/request/v20160810/QueryAccessorDomainWhiteListRequest.py
aliyunsdkbeian/request/v20160810/QueryAccessorDomainsStatusRequest.py
aliyunsdkbeian/request/v20160810/QueryAccessorIpRequest.py
aliyunsdkbeian/request/v20160810/SubmitAccessorFullDomainsOssListRequest.py
aliyunsdkbeian/request/v20160810/__init__.py
aliyun_python_sdk_beian-1.0.1.dist-info/LICENSE
aliyun_python_sdk_beian-1.0.1.dist-info/METADATA
aliyun_python_sdk_beian-1.0.1.dist-info/WHEEL
aliyun_python_sdk_beian-1.0.1.dist-info/top_level.txt
aliyun_python_sdk_beian-1.0.1.dist-info/RECORD
